office_tool_plus/__init__.py
office_tool_plus/utils.py
office_tool_plus/excel/__init__.py
office_tool_plus/excel/app.py
office_tool_plus/linux/__init__.py
office_tool_plus/linux/app.py
office_tool_plus/pdf/__init__.py
office_tool_plus/pdf/app.py
office_tool_plus/word/__init__.py
office_tool_plus/word/app.py
office_tool_plus-0.1.7.dist-info/METADATA
office_tool_plus-0.1.7.dist-info/WHEEL
office_tool_plus-0.1.7.dist-info/licenses/LICENSE
office_tool_plus-0.1.7.dist-info/RECORD
