Metadata-Version: 2.4
Name: office_tool_plus
Version: 0.1.7
Summary: 基于 Python 开发的自动化 office 工具包
Project-URL: Gitee, https://gitee.com/Muzi-Li-Chine/office_tool_plus
Project-URL: Github, https://github.com/Muzi-Li-China/office_tool_plus
Project-URL: Issues, https://gitee.com/Muzi-Li-Chine/office_tool_plus/issues
Author-email: muzili <1537080775@qq.com>
License-Expression: MIT
License-File: LICENSE
Classifier: Development Status :: 3 - Alpha
Classifier: Intended Audience :: Developers
Classifier: Natural Language :: Chinese (Simplified)
Classifier: Natural Language :: English
Classifier: Operating System :: Microsoft :: Windows
Classifier: Operating System :: POSIX :: Linux
Classifier: Programming Language :: Python :: 3
Requires-Python: >=3.6
Requires-Dist: docxtpl>=0.16.8
Requires-Dist: openpyxl>=3.0.0
Requires-Dist: pillow>=8.4.0
Requires-Dist: pywin32>=300; platform_system == 'Windows'
